Metadata-Version: 2.1
Name: bezpy
Version: 0.1.1
Summary: Geomagnetic field (B), Geoelectric field (E), and Magnetotelluric Impedance (Z) Python routines.
Author: Greg Lucas
License: Copyright (c) 2017 Greg Lucas
Project-URL: homepage, https://github.com/greglucas/bezpy
Keywords: geomagnetic,geoelectric,GIC,hazard analysis
Classifier: Development Status :: 4 - Beta
Classifier: Framework :: Matplotlib
Classifier: License :: OSI Approved :: MIT License
Classifier: Operating System :: MacOS :: MacOS X
Classifier: Operating System :: Microsoft :: Windows
Classifier: Operating System :: POSIX
Classifier: Operating System :: POSIX :: AIX
Classifier: Operating System :: POSIX :: Linux
Classifier: Programming Language :: C++
Classifier: Programming Language :: Python
Classifier: Programming Language :: Python :: 3
Classifier: Programming Language :: Python :: 3.9
Classifier: Programming Language :: Python :: 3.10
Classifier: Programming Language :: Python :: 3.11
Classifier: Programming Language :: Python :: 3 :: Only
Classifier: Topic :: Scientific/Engineering
Classifier: Topic :: Scientific/Engineering :: GIS
Classifier: Topic :: Scientific/Engineering :: Visualization
Requires-Python: >=3.9
License-File: LICENSE
Requires-Dist: numpy >=1.21
Requires-Dist: pandas >=1.3
Requires-Dist: scipy >=1.7
Requires-Dist: shapely >=1.7
Provides-Extra: plotting
Requires-Dist: matplotlib >=3.4 ; extra == 'plotting'
